gymtonic/__init__.py
gymtonic/envs/__init__.py
gymtonic/envs/_old_soccer_single_v1_.py
gymtonic/envs/block_push_v0.py
gymtonic/envs/grid_base.py
gymtonic/envs/grid_target_directional_v0.py
gymtonic/envs/grid_target_simple_v0.py
gymtonic/envs/grid_target_v0.py
gymtonic/envs/raycast.py
gymtonic/envs/soccer_single_discrete_v0.py
gymtonic/envs/soccer_single_ray_v0.py
gymtonic/envs/soccer_single_v0.py
gymtonic/envs/soccer_stadium.py
gymtonic/envs/meshes/goal.obj
gymtonic-0.1.6.dist-info/LICENSE
gymtonic-0.1.6.dist-info/METADATA
gymtonic-0.1.6.dist-info/WHEEL
gymtonic-0.1.6.dist-info/top_level.txt
gymtonic-0.1.6.dist-info/RECORD
