Metadata-Version: 2.2
Name: gymtonic
Version: 0.1.6
Summary: A set of Gymnasium compatible environments.
Author-email: Inaki Vazquez <ivazquez@deusto.es>
Project-URL: Homepage, https://github.com/inakivazquez/gymtonic
Project-URL: Issues, https://github.com/inakivazquez/gymtonic/issues
Classifier: Programming Language :: Python :: 3
Classifier: License :: OSI Approved :: GNU General Public License v3 (GPLv3)
Classifier: Operating System :: OS Independent
Requires-Python: >=3.8
License-File: LICENSE
Requires-Dist: numpy
Requires-Dist: gymnasium>=1.1.1
Requires-Dist: pybullet
Requires-Dist: mujoco
